odoo8_addon_printer_tray-8.0.1.0.1.99.dev23-py3.8-nspkg.pth
odoo_addons/printer_tray/README.rst
odoo_addons/printer_tray/__init__.py
odoo_addons/printer_tray/__openerp__.py
odoo_addons/printer_tray/ir_report.py
odoo_addons/printer_tray/ir_report_view.xml
odoo_addons/printer_tray/printer.py
odoo_addons/printer_tray/printer_tray.py
odoo_addons/printer_tray/printer_view.xml
odoo_addons/printer_tray/report_xml_action.py
odoo_addons/printer_tray/report_xml_action_view.xml
odoo_addons/printer_tray/users.py
odoo_addons/printer_tray/users_view.xml
odoo_addons/printer_tray/i18n/am.po
odoo_addons/printer_tray/i18n/ar.po
odoo_addons/printer_tray/i18n/bg.po
odoo_addons/printer_tray/i18n/bs.po
odoo_addons/printer_tray/i18n/ca.po
odoo_addons/printer_tray/i18n/ca_ES.po
odoo_addons/printer_tray/i18n/cs.po
odoo_addons/printer_tray/i18n/da.po
odoo_addons/printer_tray/i18n/de.po
odoo_addons/printer_tray/i18n/el_GR.po
odoo_addons/printer_tray/i18n/en_GB.po
odoo_addons/printer_tray/i18n/es.po
odoo_addons/printer_tray/i18n/es_AR.po
odoo_addons/printer_tray/i18n/es_CL.po
odoo_addons/printer_tray/i18n/es_CO.po
odoo_addons/printer_tray/i18n/es_CR.po
odoo_addons/printer_tray/i18n/es_DO.po
odoo_addons/printer_tray/i18n/es_EC.po
odoo_addons/printer_tray/i18n/es_ES.po
odoo_addons/printer_tray/i18n/es_MX.po
odoo_addons/printer_tray/i18n/es_PE.po
odoo_addons/printer_tray/i18n/es_PY.po
odoo_addons/printer_tray/i18n/es_VE.po
odoo_addons/printer_tray/i18n/et.po
odoo_addons/printer_tray/i18n/eu.po
odoo_addons/printer_tray/i18n/fa.po
odoo_addons/printer_tray/i18n/fi.po
odoo_addons/printer_tray/i18n/fr.po
odoo_addons/printer_tray/i18n/fr_CA.po
odoo_addons/printer_tray/i18n/fr_CH.po
odoo_addons/printer_tray/i18n/gl.po
odoo_addons/printer_tray/i18n/gl_ES.po
odoo_addons/printer_tray/i18n/he.po
odoo_addons/printer_tray/i18n/hr.po
odoo_addons/printer_tray/i18n/hr_HR.po
odoo_addons/printer_tray/i18n/hu.po
odoo_addons/printer_tray/i18n/id.po
odoo_addons/printer_tray/i18n/it.po
odoo8_addon_printer_tray-8.0.1.0.1.99.dev23.dist-info/METADATA
odoo8_addon_printer_tray-8.0.1.0.1.99.dev23.dist-info/WHEEL
odoo8_addon_printer_tray-8.0.1.0.1.99.dev23.dist-info/namespace_packages.txt
odoo8_addon_printer_tray-8.0.1.0.1.99.dev23.dist-info/top_level.txt
odoo8_addon_printer_tray-8.0.1.0.1.99.dev23.dist-info/RECORD
